{
  "基础信息": {
    "姓名": "李xx",
    "性别": "女",
    "年龄": "33"
  },
  "人格": {
    "性格": "偏执",
    "情绪状态": "平稳",
    "病史回忆能力": "高",
    "医学理解力": "低",
    "语言表达能力": "中"
  },
  "门诊病历": {
    "主诉": "要求呼气试验",
    "现病史": "同上",
    "流行病学史": "无",
    "既往史": "既往体健",
    "药物过敏史": "无。",
    "体格检查": "无专科阳性体征",
    "辅助检查": "2025/5/26，碳13呼气试验，阳性",
    "处理": "无",
    "注意事项": "如无过敏等禁忌症：除菌方案：沃克20mg、枸機酸铋钾220mg2次/日，餐前半小时口服，阿莫西林1000mg，克拉霉素500mg2次/日，餐后口服，疗程14天，停药1个月后复查C13，服药期间禁烟酒，如遇不适，及时随诊，注意监测肝肾功。建议胃镜、肝胆胰彩超（拒绝）定期复查，病变随诊",
    "患者去向": "离院",
    "备注": "无"
  },
  "检验": "无",
  "检查": [
    {
      "序号": "1",
      "检查名称": "碳13呼气试验",
      "报告时间": "2025-05-26 09:02",
      "检查描述": "阳性",
      "检查报告": "阳性"
    }
  ],
  "主诊断": "幽门螺杆菌感染",
  "申请单": [
    {
      "序号": "1",
      "类别": "检查",
      "医嘱名称": "碳13呼气试验"
    }
  ],
  "处方单1(西成方）": [],
  "门诊对话": [
    {
      "轮次": 1,
      "医生": "xxx是吧？​",
      "患者": "是。我就是有的时候吃点中成药，就是那种颗粒的，吃个两三天之后就感觉胃疼。​"
    },
    {
      "轮次": 2,
      "医生": "为啥要吃中成药？​",
      "患者": "就是管气血不足的。生了孩子之后就气血不足，没劲儿，还特别怕冷，风一吹头就疼，所以总戴帽子，夏天也不能穿裙子。​"
    },
    {
      "轮次": 3,
      "医生": "你觉得吃那药管用吗？​",
      "患者": "管用，但吃着吃着胃就疼。我胃不太好，想查一下幽门螺旋杆菌。​"
    },
    {
      "轮次": 4,
      "医生": "一个月之内吃没吃抗生素、奥美拉唑这些？​",
      "患者": "奥美拉唑没吃，但吃了一点中药，也是管气血虚弱的。​"
    },
    {
      "轮次": 5,
      "医生": "中药成分不确定，那咱先检查看看。你应该做个胃镜。​",
      "患者": "我不想做胃镜，太遭罪了。​"
    },
    {
      "轮次": 6,
      "医生": "哪个地方难受？你比划一下。​",
      "患者": "就是这一块，就这一片都闷闷的疼，感觉像胃炎，我胃一直不太好。​"
    },
    {
      "轮次": 7,
      "医生": "建议你查个胃镜和肝胆胰彩超，你要是不想做，我也没法准确判断啊。​",
      "患者": "胃镜太遭罪了，我真不想做，听着都害怕。​"
    },
    {
      "轮次": 8,
      "医生": "那你先查个吹气试验吧。​",
      "患者": "行，就吹个气。​"
    },
    {
      "轮次": 9,
      "医生": "你今天没吃没喝吧？​",
      "患者": "中午吃的饭，这行吗？​"
    },
    {
      "轮次": 10,
      "医生": "得空腹两小时以上才行。​",
      "患者": "那我交了钱明天再来吧​"
    },
    {
      "轮次": 11,
      "医生": "可以​",
      "患者": "平时就感觉有胃炎，只要一吃中药，两三天后胃就难受。去年还吃了半个月医生开的抑制胃酸的药，之后胃疼了两周，每天都疼。我感觉我胃挺差的。​"
    },
    {
      "轮次": 12,
      "医生": "要是害怕做胃镜，可以做无痛的。​",
      "患者": "无痛的不是得有人陪同吗？我一个人来的。那之后能给我开点管胃炎的药吗？​"
    },
    {
      "轮次": 13,
      "医生": "你先做吹气试验吧，不然吃完药结果就不准了。​",
      "患者": "反正我这胃就是不太好​"
    },
    {
      "轮次": 14,
      "医生": "开药的话只能开点奥美拉唑之类的，​",
      "患者": "就是只能吃奥美拉唑是吗​"
    },
    {
      "轮次": 15,
      "医生": "不是那你想吃点啥？​",
      "患者": "不是我先不吃，就是说之后能不能开点管胃的，中成药就行，让胃好点。​"
    },
    {
      "轮次": 16,
      "医生": "你应该挂个中医科，感觉你比较排斥西药。​",
      "患者": "我没有排斥西药，只要能把我这病治好就行。​"
    },
    {
      "轮次": 17,
      "医生": "没人能保证一定治好，因为还不知道病因。你有没有幽门螺杆菌感染​",
      "患者": "好几年前做过​"
    },
    {
      "轮次": 18,
      "医生": "你有胃溃疡、胃糜烂吗？这些都得检查才知道。不找原因就没法对症治疗啊，医学得实事求是。你可以先做吹气试验看看。​",
      "患者": "胃镜我真是一点也不想做，我老公做过，我看着就害怕。​"
    },
    {
      "轮次": 19,
      "医生": "现在无痛胃镜不疼，睡一觉就完事了，很多人都做。​",
      "患者": "这个吹气必须两小时以上吗？​"
    },
    {
      "轮次": 20,
      "医生": "对，你去预约处再问问具体要求吧。​",
      "患者": "好的，谢谢。​"
    }
  ]
}