{
  "基础信息": {
    "姓名": "何抒睿",
    "性别": "女",
    "年龄": "32"
  },
  "人格": {
    "性格": "合作",
    "情绪状态": "平稳",
    "病史回忆能力": "高",
    "医学理解力": "高",
    "语言表达能力": "中"
  },
  "门诊病历": {
    "主诉": "间断胃区不适2-3天",
    "现病史": "餐后恶心、呕吐;暖气;消化欠佳",
    "流行病学史": "无",
    "既往史": "既往体健。无药物过敏史。",
    "药物过敏史": "无",
    "体格检查": "无专科阳性特征",
    "辅助检查": "无",
    "处理": "无",
    "注意事项": "口服舒丽启能，有变化随诊",
    "患者去向": "离院",
    "备注": "无"
  },
  "检验": "无",
  "检查": "无",
  "主诊断": "恶心",
  "申请单": [],
  "处方单1(西成方）": [],
  "门诊对话": [
    {
      "轮次": 1,
      "医生": "都怎么了哪不舒服，",
      "患者": "胃有点，吃东西完了就恶心，消化就特别慢了。"
    },
    {
      "轮次": 2,
      "医生": "胃恶心，吐吗？",
      "患者": "吃多了就会有点反。"
    },
    {
      "轮次": 3,
      "医生": "恶心，不吐出来是不是",
      "患者": "也吐，但不是那种哇哇吐。"
    },
    {
      "轮次": 4,
      "医生": "吐的是什么？是饭吗？还是？粘液就水什么的，",
      "患者": "像反正也有点像水似的，"
    },
    {
      "轮次": 5,
      "医生": "像水似的，你这样症状多长时间了？",
      "患者": "就前两三天。"
    },
    {
      "轮次": 6,
      "医生": "一共就两三天的时间是吧？这两三天是天天都这样吗。",
      "患者": "反正有，连着前两天是这样。"
    },
    {
      "轮次": 7,
      "医生": "恶心是一般是吃完饭恶心还是饿的时候恶心？",
      "患者": "吃完饭，还有就是刚起来的时候。"
    },
    {
      "轮次": 8,
      "医生": "刚起来还没吃饭，早上起来没吃饭的时候恶心。除了恶心吐之外还有别的症状吗？比如说什么胃疼、反酸、水、烧心、打嗝这样的症状。",
      "患者": "有点打嗝，"
    },
    {
      "轮次": 9,
      "医生": "打嗝啊，不明显？",
      "患者": "不太明显。"
    },
    {
      "轮次": 10,
      "医生": "影响吃饭吗",
      "患者": "感觉可能是我前段时间吃的比较少，然后现在一吃东西就感觉..."
    },
    {
      "轮次": 11,
      "医生": "比较少，是自己控制的？",
      "患者": "前段时间三天没吃饭。半夜吃牛肉，"
    },
    {
      "轮次": 12,
      "医生": "你半夜吃牛肉干，然后出现这样的症状了，你大便有没有拉肚什么？",
      "患者": "有点拉"
    },
    {
      "轮次": 13,
      "医生": "拉肚是一天拉几次？",
      "患者": "之前好像一天三四次。"
    },
    {
      "轮次": 14,
      "医生": "三四次也是这三天的事，现在还是比较多？",
      "患者": "这两天都没咋吃这个东西"
    },
    {
      "轮次": 15,
      "医生": "然后就没排便？",
      "患者": "嗯嗯"
    },
    {
      "轮次": 16,
      "医生": "没有发烧啥的？",
      "患者": "没有"
    },
    {
      "轮次": 17,
      "医生": "后背疼吗？腰疼肩膀疼这些都没有？",
      "患者": "没有"
    },
    {
      "轮次": 18,
      "医生": "以前从来都没有过这样的症状吗？",
      "患者": "没有"
    },
    {
      "轮次": 19,
      "医生": "原来还得过其他的啥病吗？特殊的什么病，",
      "患者": "特殊的就..."
    },
    {
      "轮次": 20,
      "医生": "就诊断过啥病",
      "患者": "没有"
    },
    {
      "轮次": 21,
      "医生": "没有啥特殊的是吧？因为没有症状，没做过胃镜啥的是吧？我看一下疼不疼，我再按什么摸一下。不疼，都不疼？",
      "患者": "就是恶心"
    },
    {
      "轮次": 22,
      "医生": "你要是也就两三天的时间的话，你也可以先吃药观察一下，也有可能就是说吃饮食不规律，然后吃了硬的东西，就胃肠功能紊乱了，也有这种可能性，因为病史病程不是特别长，如果要是还是不行的话，可以进一步做检查胃镜什么的",
      "患者": "那也行，你给我吃点啥药"
    },
    {
      "轮次": 23,
      "医生": "对，我是建议先吃点药调理一下。",
      "患者": "那也行。"
    },
    {
      "轮次": 24,
      "医生": "我给你写几种药，",
      "患者": "行，我先吃点药"
    }
  ]
}